llm_toys/__init__.py
llm_toys/config.py
llm_toys/eval.py
llm_toys/prompts.py
llm_toys/train.py
llm_toys/utils.py
llm_toys/hf/__init__.py
llm_toys/hf/peft/__init__.py
llm_toys/hf/peft/auto.py
llm_toys/hf/peft/import_utils.py
llm_toys/hf/peft/mapping.py
llm_toys/hf/peft/peft_model.py
llm_toys/hf/peft/tuners/__init__.py
llm_toys/hf/peft/tuners/adalora.py
llm_toys/hf/peft/tuners/adaption_prompt.py
llm_toys/hf/peft/tuners/ia3.py
llm_toys/hf/peft/tuners/lora.py
llm_toys/hf/peft/tuners/p_tuning.py
llm_toys/hf/peft/tuners/prefix_tuning.py
llm_toys/hf/peft/tuners/prompt_tuning.py
llm_toys/hf/peft/utils/__init__.py
llm_toys/hf/peft/utils/config.py
llm_toys/hf/peft/utils/hub_utils.py
llm_toys/hf/peft/utils/other.py
llm_toys/hf/peft/utils/save_and_load.py
llm_toys/hf/transformers/__init__.py
llm_toys/hf/transformers/activations.py
llm_toys/hf/transformers/activations_tf.py
llm_toys/hf/transformers/audio_utils.py
llm_toys/hf/transformers/configuration_utils.py
llm_toys/hf/transformers/convert_graph_to_onnx.py
llm_toys/hf/transformers/convert_pytorch_checkpoint_to_tf2.py
llm_toys/hf/transformers/convert_slow_tokenizer.py
llm_toys/hf/transformers/convert_slow_tokenizers_checkpoints_to_fast.py
llm_toys/hf/transformers/convert_tf_hub_seq_to_seq_bert_to_pytorch.py
llm_toys/hf/transformers/debug_utils.py
llm_toys/hf/transformers/deepspeed.py
llm_toys/hf/transformers/dependency_versions_check.py
llm_toys/hf/transformers/dependency_versions_table.py
llm_toys/hf/transformers/dynamic_module_utils.py
llm_toys/hf/transformers/feature_extraction_sequence_utils.py
llm_toys/hf/transformers/feature_extraction_utils.py
llm_toys/hf/transformers/file_utils.py
llm_toys/hf/transformers/generation_flax_utils.py
llm_toys/hf/transformers/generation_tf_utils.py
llm_toys/hf/transformers/generation_utils.py
llm_toys/hf/transformers/hf_argparser.py
llm_toys/hf/transformers/hyperparameter_search.py
llm_toys/hf/transformers/image_processing_utils.py
llm_toys/hf/transformers/image_transforms.py
llm_toys-0.1.1.dist-info/METADATA
llm_toys-0.1.1.dist-info/WHEEL
llm_toys-0.1.1.dist-info/top_level.txt
llm_toys-0.1.1.dist-info/RECORD
